sdformat14/__init__.py
sdformat14/sdformat14.cpython-311-x86_64-linux-gnu.so
sdformat14_py_bindings-1.0.0.dist-info/LICENSE
sdformat14_py_bindings-1.0.0.dist-info/METADATA
sdformat14_py_bindings-1.0.0.dist-info/WHEEL
sdformat14_py_bindings-1.0.0.dist-info/top_level.txt
sdformat14_py_bindings-1.0.0.dist-info/RECORD
