Metadata-Version: 2.1
Name: sdformat14-py-bindings
Version: 1.0.0
Summary: Python 3.11 bindings for Gazebo sdformat14 library
Home-page: https://github.com/Jc-Cloete
Author: Jc Cloete
Author-email: Jc Cloete <jc@truevolve.technology>
License: Apache License
Project-URL: Homepage, https://github.com/Jc-Cloete
Project-URL: Issues, https://github.com/Jc-Cloete
Classifier: Programming Language :: Python :: 3.11
Classifier: License :: OSI Approved :: Apache Software License
Classifier: Operating System :: POSIX :: Linux
Classifier: Development Status :: 4 - Beta
Requires-Python: >=3.11
License-File: LICENSE
